README.rst
birds/__init__.py
birds/admin.py
birds/api_views.py
birds/apps.py
birds/filters.py
birds/forms.py
birds/models.py
birds/pedigree.py
birds/serializers.py
birds/tools.py
birds/triggers.py
birds/urls.py
birds/views.py
birds/fixtures/bird_colony_sandbox.json
birds/fixtures/bird_colony_starter_kit.json
birds/management/commands/migrate_measurements.py
birds/management/commands/update_life_history.py
birds/migrations/0001_initial.py
birds/migrations/0002_auto_20180130_1706.py
birds/migrations/0003_auto_20180322_1617.py
birds/migrations/0004_auto_20180322_1729.py
birds/migrations/0005_auto_20190119_1603.py
birds/migrations/0006_auto_20190125_1453.py
birds/migrations/0007_auto_20190205_1534.py
birds/migrations/0008_auto_20190703_1230.py
birds/migrations/0009_remove_age_max_days.py
birds/migrations/0010_location_nest.py
birds/migrations/0011_auto_20200110_1510.py
birds/migrations/0012_auto_20200116_1141.py
birds/migrations/0013_auto_20220330_1214.py
birds/migrations/0014_auto_20220401_1217.py
birds/migrations/0015_event_animal_status_idx.py
birds/migrations/0016_event_animal_date_idx.py
birds/migrations/0017_pairing_ended_gt_began.py
birds/migrations/0018_alter_pairing_options_remove_pairing_ended_gt_began_and_more.py
birds/migrations/0019_location_description.py
birds/migrations/0020_measure_alter_age_options_alter_color_options_and_more.py
birds/migrations/0021_alter_measurement_event_alter_sample_date.py
birds/migrations/0022_status_removes_to_enum_20250602_1225.py
birds/migrations/0023_alter_status_adds_alter_status_removes.py
birds/migrations/0024_add_status_constraint_and_indices.py
birds/migrations/0025_parent_parent_idx_parent_child_idx.py
birds/migrations/0026_fix_parent_created_timestamps.py
birds/migrations/0027_alter_status_adds_animallifehistory.py
birds/migrations/0028_animallifehistory_last_location_and_more.py
birds/migrations/0029_remove_animallifehistory_has_any_event_and_more.py
birds/migrations/0030_animallifehistory_inbreeding_coefficient.py
django_bird_colony-0.14.0.dist-info/METADATA
django_bird_colony-0.14.0.dist-info/WHEEL
django_bird_colony-0.14.0.dist-info/licenses/COPYING
django_bird_colony-0.14.0.dist-info/RECORD
